{
  "meta": {
    "title": "Mobile Money Account",
    "valueLabel": "Adults (15+) with a mobile-money account",
    "unit": "%",
    "changeMode": "pp",
    "topic": "economy",
    "summary": "Share of adults (15+) with a mobile-money account (e.g. M-Pesa) — fintech beyond traditional banks. World Bank Global Findex.",
    "source": "World Bank Open Data",
    "license": "CC BY 4.0",
    "url": "https://data.worldbank.org/",
    "parsedAt": "2026-07-07",
    "kind": "macro"
  },
  "data": [
    {
      "entity": "Afghanistan",
      "group": "Asia",
      "period": "2021",
      "value": 0,
      "iso": "AFG"
    },
    {
      "entity": "Albania",
      "group": "Europe",
      "period": "2017",
      "value": 2.38,
      "iso": "ALB"
    },
    {
      "entity": "Argentina",
      "group": "Americas",
      "period": "2024",
      "value": 56.74,
      "iso": "ARG"
    },
    {
      "entity": "Armenia",
      "group": "Europe",
      "period": "2024",
      "value": 17.36,
      "iso": "ARM"
    },
    {
      "entity": "Bangladesh",
      "group": "Asia",
      "period": "2024",
      "value": 20.77,
      "iso": "BGD"
    },
    {
      "entity": "Belize",
      "group": "Americas",
      "period": "2024",
      "value": 13.67,
      "iso": "BLZ"
    },
    {
      "entity": "Benin",
      "group": "Africa",
      "period": "2024",
      "value": 44.87,
      "iso": "BEN"
    },
    {
      "entity": "Bolivia",
      "group": "Americas",
      "period": "2024",
      "value": 19.98,
      "iso": "BOL"
    },
    {
      "entity": "Botswana",
      "group": "Africa",
      "period": "2024",
      "value": 51.62,
      "iso": "BWA"
    },
    {
      "entity": "Brazil",
      "group": "Americas",
      "period": "2024",
      "value": 58.17,
      "iso": "BRA"
    },
    {
      "entity": "Burkina Faso",
      "group": "Africa",
      "period": "2024",
      "value": 44.16,
      "iso": "BFA"
    },
    {
      "entity": "Burundi",
      "group": "Africa",
      "period": "2014",
      "value": 0.75,
      "iso": "BDI"
    },
    {
      "entity": "Cambodia",
      "group": "Asia",
      "period": "2024",
      "value": 16.89,
      "iso": "KHM"
    },
    {
      "entity": "Cameroon",
      "group": "Africa",
      "period": "2024",
      "value": 55.07,
      "iso": "CMR"
    },
    {
      "entity": "Chad",
      "group": "Africa",
      "period": "2024",
      "value": 13.34,
      "iso": "TCD"
    },
    {
      "entity": "Chile",
      "group": "Americas",
      "period": "2017",
      "value": 18.67,
      "iso": "CHL"
    },
    {
      "entity": "Colombia",
      "group": "Americas",
      "period": "2024",
      "value": 39.15,
      "iso": "COL"
    },
    {
      "entity": "Comoros",
      "group": "Africa",
      "period": "2024",
      "value": 14.09,
      "iso": "COM"
    },
    {
      "entity": "Congo, Dem. Rep.",
      "group": "Africa",
      "period": "2024",
      "value": 35.12,
      "iso": "COD"
    },
    {
      "entity": "Congo, Rep.",
      "group": "Africa",
      "period": "2024",
      "value": 51.59,
      "iso": "COG"
    },
    {
      "entity": "Cote d'Ivoire",
      "group": "Africa",
      "period": "2024",
      "value": 53.38,
      "iso": "CIV"
    },
    {
      "entity": "Dominican Republic",
      "group": "Americas",
      "period": "2024",
      "value": 18.02,
      "iso": "DOM"
    },
    {
      "entity": "Ecuador",
      "group": "Americas",
      "period": "2024",
      "value": 10.08,
      "iso": "ECU"
    },
    {
      "entity": "Egypt",
      "group": "Africa",
      "period": "2024",
      "value": 15.61,
      "iso": "EGY"
    },
    {
      "entity": "El Salvador",
      "group": "Americas",
      "period": "2024",
      "value": 5.84,
      "iso": "SLV"
    },
    {
      "entity": "Eswatini",
      "group": "Africa",
      "period": "2024",
      "value": 50.41,
      "iso": "SWZ"
    },
    {
      "entity": "Ethiopia",
      "group": "Africa",
      "period": "2024",
      "value": 9.45,
      "iso": "ETH"
    },
    {
      "entity": "Gabon",
      "group": "Africa",
      "period": "2024",
      "value": 61.64,
      "iso": "GAB"
    },
    {
      "entity": "Gambia",
      "group": "Africa",
      "period": "2024",
      "value": 19.09,
      "iso": "GMB"
    },
    {
      "entity": "Georgia",
      "group": "Europe",
      "period": "2021",
      "value": 8.23,
      "iso": "GEO"
    },
    {
      "entity": "Ghana",
      "group": "Africa",
      "period": "2024",
      "value": 78.28,
      "iso": "GHA"
    },
    {
      "entity": "Guatemala",
      "group": "Americas",
      "period": "2024",
      "value": 3.3,
      "iso": "GTM"
    },
    {
      "entity": "Guinea",
      "group": "Africa",
      "period": "2024",
      "value": 25.82,
      "iso": "GIN"
    },
    {
      "entity": "Haiti",
      "group": "Americas",
      "period": "2017",
      "value": 13.52,
      "iso": "HTI"
    },
    {
      "entity": "Honduras",
      "group": "Americas",
      "period": "2024",
      "value": 10.89,
      "iso": "HND"
    },
    {
      "entity": "India",
      "group": "Asia",
      "period": "2024",
      "value": 23.1,
      "iso": "IND"
    },
    {
      "entity": "Indonesia",
      "group": "Asia",
      "period": "2024",
      "value": 22.01,
      "iso": "IDN"
    },
    {
      "entity": "Iran",
      "group": "Asia",
      "period": "2024",
      "value": 13.1,
      "iso": "IRN"
    },
    {
      "entity": "Iraq",
      "group": "Asia",
      "period": "2024",
      "value": 11.86,
      "iso": "IRQ"
    },
    {
      "entity": "Jamaica",
      "group": "Americas",
      "period": "2021",
      "value": 12.66,
      "iso": "JAM"
    },
    {
      "entity": "Jordan",
      "group": "Asia",
      "period": "2024",
      "value": 20.56,
      "iso": "JOR"
    },
    {
      "entity": "Kazakhstan",
      "group": "Asia",
      "period": "2024",
      "value": 48.86,
      "iso": "KAZ"
    },
    {
      "entity": "Kenya",
      "group": "Africa",
      "period": "2024",
      "value": 87.5,
      "iso": "KEN"
    },
    {
      "entity": "South Korea",
      "group": "Asia",
      "period": "2024",
      "value": 60.1,
      "iso": "KOR"
    },
    {
      "entity": "Kyrgyz Republic",
      "group": "Asia",
      "period": "2024",
      "value": 31.04,
      "iso": "KGZ"
    },
    {
      "entity": "Lao",
      "group": "Asia",
      "period": "2024",
      "value": 11.84,
      "iso": "LAO"
    },
    {
      "entity": "Lebanon",
      "group": "Asia",
      "period": "2024",
      "value": 2.72,
      "iso": "LBN"
    },
    {
      "entity": "Lesotho",
      "group": "Africa",
      "period": "2024",
      "value": 53.47,
      "iso": "LSO"
    },
    {
      "entity": "Liberia",
      "group": "Africa",
      "period": "2024",
      "value": 47.53,
      "iso": "LBR"
    },
    {
      "entity": "Madagascar",
      "group": "Africa",
      "period": "2024",
      "value": 19.36,
      "iso": "MDG"
    },
    {
      "entity": "Malawi",
      "group": "Africa",
      "period": "2024",
      "value": 47.4,
      "iso": "MWI"
    },
    {
      "entity": "Malaysia",
      "group": "Asia",
      "period": "2024",
      "value": 44.5,
      "iso": "MYS"
    },
    {
      "entity": "Maldives",
      "group": "Asia",
      "period": "2017",
      "value": 23.3,
      "iso": "MDV"
    },
    {
      "entity": "Mali",
      "group": "Africa",
      "period": "2024",
      "value": 48.39,
      "iso": "MLI"
    },
    {
      "entity": "Mauritania",
      "group": "Africa",
      "period": "2022",
      "value": 10.16,
      "iso": "MRT"
    },
    {
      "entity": "Mauritius",
      "group": "Africa",
      "period": "2024",
      "value": 10.13,
      "iso": "MUS"
    },
    {
      "entity": "Mexico",
      "group": "Americas",
      "period": "2024",
      "value": 10.44,
      "iso": "MEX"
    },
    {
      "entity": "Mongolia",
      "group": "Asia",
      "period": "2024",
      "value": 64.03,
      "iso": "MNG"
    },
    {
      "entity": "Morocco",
      "group": "Africa",
      "period": "2024",
      "value": 5.88,
      "iso": "MAR"
    },
    {
      "entity": "Mozambique",
      "group": "Africa",
      "period": "2024",
      "value": 45.72,
      "iso": "MOZ"
    },
    {
      "entity": "Myanmar",
      "group": "Asia",
      "period": "2021",
      "value": 29.03,
      "iso": "MMR"
    },
    {
      "entity": "Namibia",
      "group": "Africa",
      "period": "2024",
      "value": 48.45,
      "iso": "NAM"
    },
    {
      "entity": "Nepal",
      "group": "Asia",
      "period": "2024",
      "value": 10.58,
      "iso": "NPL"
    },
    {
      "entity": "Nicaragua",
      "group": "Americas",
      "period": "2024",
      "value": 8.09,
      "iso": "NIC"
    },
    {
      "entity": "Niger",
      "group": "Africa",
      "period": "2024",
      "value": 5.7,
      "iso": "NER"
    },
    {
      "entity": "Nigeria",
      "group": "Africa",
      "period": "2024",
      "value": 32.79,
      "iso": "NGA"
    },
    {
      "entity": "Pakistan",
      "group": "Asia",
      "period": "2024",
      "value": 18.36,
      "iso": "PAK"
    },
    {
      "entity": "Panama",
      "group": "Americas",
      "period": "2024",
      "value": 38.05,
      "iso": "PAN"
    },
    {
      "entity": "Paraguay",
      "group": "Americas",
      "period": "2024",
      "value": 35.95,
      "iso": "PRY"
    },
    {
      "entity": "Peru",
      "group": "Americas",
      "period": "2024",
      "value": 42.5,
      "iso": "PER"
    },
    {
      "entity": "Philippines",
      "group": "Asia",
      "period": "2024",
      "value": 28.8,
      "iso": "PHL"
    },
    {
      "entity": "Romania",
      "group": "Europe",
      "period": "2017",
      "value": 2.99,
      "iso": "ROU"
    },
    {
      "entity": "Russia",
      "group": "Europe",
      "period": "2024",
      "value": 5.82,
      "iso": "RUS"
    },
    {
      "entity": "Rwanda",
      "group": "Africa",
      "period": "2017",
      "value": 31.11,
      "iso": "RWA"
    },
    {
      "entity": "Saudi Arabia",
      "group": "Asia",
      "period": "2024",
      "value": 36.5,
      "iso": "SAU"
    },
    {
      "entity": "Senegal",
      "group": "Africa",
      "period": "2024",
      "value": 66.91,
      "iso": "SEN"
    },
    {
      "entity": "Sierra Leone",
      "group": "Africa",
      "period": "2024",
      "value": 32.2,
      "iso": "SLE"
    },
    {
      "entity": "Singapore",
      "group": "Asia",
      "period": "2024",
      "value": 56.47,
      "iso": "SGP"
    },
    {
      "entity": "Somalia",
      "group": "Africa",
      "period": "2014",
      "value": 37.07,
      "iso": "SOM"
    },
    {
      "entity": "South Africa",
      "group": "Africa",
      "period": "2024",
      "value": 31.62,
      "iso": "ZAF"
    },
    {
      "entity": "South Sudan",
      "group": "Africa",
      "period": "2021",
      "value": 0.85,
      "iso": "SSD"
    },
    {
      "entity": "Sri Lanka",
      "group": "Asia",
      "period": "2024",
      "value": 3,
      "iso": "LKA"
    },
    {
      "entity": "Tajikistan",
      "group": "Asia",
      "period": "2024",
      "value": 14.43,
      "iso": "TJK"
    },
    {
      "entity": "Tanzania",
      "group": "Africa",
      "period": "2024",
      "value": 52.85,
      "iso": "TZA"
    },
    {
      "entity": "Thailand",
      "group": "Asia",
      "period": "2024",
      "value": 41.68,
      "iso": "THA"
    },
    {
      "entity": "Togo",
      "group": "Africa",
      "period": "2024",
      "value": 47.99,
      "iso": "TGO"
    },
    {
      "entity": "Tunisia",
      "group": "Africa",
      "period": "2024",
      "value": 2.65,
      "iso": "TUN"
    },
    {
      "entity": "Turkey",
      "group": "Europe",
      "period": "2024",
      "value": 23.32,
      "iso": "TUR"
    },
    {
      "entity": "Uganda",
      "group": "Africa",
      "period": "2024",
      "value": 67.74,
      "iso": "UGA"
    },
    {
      "entity": "UAE",
      "group": "Asia",
      "period": "2021",
      "value": 13.26,
      "iso": "ARE"
    },
    {
      "entity": "Uruguay",
      "group": "Americas",
      "period": "2014",
      "value": 1.23,
      "iso": "URY"
    },
    {
      "entity": "Venezuela",
      "group": "Americas",
      "period": "2024",
      "value": 33.74,
      "iso": "VEN"
    },
    {
      "entity": "Vietnam",
      "group": "Asia",
      "period": "2024",
      "value": 38.72,
      "iso": "VNM"
    },
    {
      "entity": "Palestine",
      "group": "Asia",
      "period": "2024",
      "value": 6.16,
      "iso": "PSE"
    },
    {
      "entity": "Zambia",
      "group": "Africa",
      "period": "2024",
      "value": 69.31,
      "iso": "ZMB"
    },
    {
      "entity": "Zimbabwe",
      "group": "Africa",
      "period": "2024",
      "value": 43.33,
      "iso": "ZWE"
    }
  ]
}
